nacos_sdk_rust_binding_py-0.4.0.dist-info/METADATA
nacos_sdk_rust_binding_py-0.4.0.dist-info/WHEEL
nacos_sdk_rust_binding_py-0.4.0.dist-info/license_files/LICENSE
nacos_sdk_rust_binding_py/__init__.py
nacos_sdk_rust_binding_py/__init__.pyi
nacos_sdk_rust_binding_py/py.typed
nacos_sdk_rust_binding_py/nacos_sdk_rust_binding_py.pypy38-pp73-x86-linux-gnu.so
nacos_sdk_rust_binding_py-0.4.0.dist-info/RECORD
