Metadata-Version: 2.3
Name: nacos-sdk-rust-binding-py
Version: 0.4.0
Classifier: Programming Language :: Rust
Classifier: Programming Language :: Python :: Implementation :: CPython
Classifier: Programming Language :: Python :: Implementation :: PyPy
Requires-Dist: pdoc ; extra == 'docs'
Requires-Dist: behave ; extra == 'test'
Provides-Extra: docs
Provides-Extra: test
License-File: LICENSE
Summary: nacos-sdk-rust binding for Python.
Keywords: nacos,ffi,pyo3,binding,python
Author: CheirshCai <785427346@qq.com>
Author-email: CheirshCai <785427346@qq.com>
License: Apache-2.0
Requires-Python: >=3.7
Project-URL: Documentation, https://github.com/opc-source/nacos-sdk-rust-binding-py.git
Project-URL: Homepage, https://github.com/opc-source/nacos-sdk-rust-binding-py.git
Project-URL: Repository, https://github.com/opc-source/nacos-sdk-rust-binding-py.git
